LICENSE
MANIFEST.in
NOTICE
README.md
VERSION
setup.cfg
setup.py
sagemaker_inference.egg-info/PKG-INFO
sagemaker_inference.egg-info/SOURCES.txt
sagemaker_inference.egg-info/dependency_links.txt
sagemaker_inference.egg-info/requires.txt
sagemaker_inference.egg-info/top_level.txt
src/sagemaker_inference/__init__.py
src/sagemaker_inference/content_types.py
src/sagemaker_inference/decoder.py
src/sagemaker_inference/default_handler_service.py
src/sagemaker_inference/default_inference_handler.py
src/sagemaker_inference/encoder.py
src/sagemaker_inference/environment.py
src/sagemaker_inference/errors.py
src/sagemaker_inference/logging.py
src/sagemaker_inference/model_server.py
src/sagemaker_inference/parameters.py
src/sagemaker_inference/transformer.py
src/sagemaker_inference/utils.py
src/sagemaker_inference/etc/default-mms.properties
src/sagemaker_inference/etc/log4j2.xml
src/sagemaker_inference/etc/mme-mms.properties