Metadata-Version: 2.1
Name: sagemaker-inference
Version: 1.5.10
Summary: Open source toolkit for helping create serving containers to run on Amazon SageMaker.
Home-page: https://github.com/aws/sagemaker-inference-toolkit/
Author: Amazon Web Services
License: Apache License 2.0
Platform: UNKNOWN
Classifier: Development Status :: 5 - Production/Stable
Classifier: Intended Audience :: Developers
Classifier: Natural Language :: English
Classifier: License :: OSI Approved :: Apache Software License
Classifier: Programming Language :: Python
Classifier: Programming Language :: Python :: 2.7
Classifier: Programming Language :: Python :: 3.6
Classifier: Programming Language :: Python :: 3.7
Provides-Extra: test
